lintersmagic.py
lintersmagic-0.1.6.dist-info/LICENSE
lintersmagic-0.1.6.dist-info/WHEEL
lintersmagic-0.1.6.dist-info/METADATA
lintersmagic-0.1.6.dist-info/RECORD
