Metadata-Version: 2.1
Name: lintersmagic
Version: 0.1.6
Summary: A package to include linters in Databricks notebooks: pycodestyle
Home-page: https://github.com/BedrockStreaming/lintersmagic
Author: Bedrock streaming
Requires-Python: ==3.8.10
Classifier: Programming Language :: Python :: 3
Requires-Dist: ipython (==8.1.1)
Requires-Dist: pycodestyle (==2.8.0)
Project-URL: Repository, https://github.com/BedrockStreaming/lintersmagic
